{
    "audio_preview_url": "https://podz-content.spotifycdn.com/audio/clips/1lzqWGVCFnGNF7h3rlfpSC/clip_485222_545222.mp3",
    "description": "Fr. Mike expands on Ezekiel 33 and emphasizes that the role of a prophet, is to be God's watchman and speak whatever it is God wants to be spoken.  He stresses the reality that those who are teachers and leaders, who shape and form the consciences of others, have the responsibility to speak the truth even when it's hard. Today's readings are Jeremiah 5, Ezekiel 33, and Proverbs 14:21-24. For the complete reading plan, visit ascensionpress.com/bibleinayear. Please note: The Bible contains adult themes that may not be suitable for children - parental discretion is advised.",
    "duration_ms": 1549609,
    "explicit": false,
    "external_urls": {
        "spotify": "https://open.spotify.com/episode/0iurdfxAfRDdIC78oHCyPA"
    },
    "href": "https://api.spotify.com/v1/episodes/0iurdfxAfRDdIC78oHCyPA",
    "html_description": "<p>Fr. Mike expands on Ezekiel 33 and emphasizes that the role of a prophet, is to be God&#39;s watchman and speak whatever it is God wants to be spoken.  He stresses the reality that those who are teachers and leaders, who shape and form the consciences of others, have the responsibility to speak the truth even when it&#39;s hard. Today&#39;s readings are Jeremiah 5, Ezekiel 33, and Proverbs 14:21-24.</p><br/><p>For the complete reading plan, visit ascensionpress.com/bibleinayear.</p><br/><p>Please note: The Bible contains adult themes that may not be suitable for children - parental discretion is advised.</p><p><a href=\"https://ascensionpress.com/products/support-ascension\" rel=\"nofollow\">Support The Bible in a Year (with Fr. Mike Schmitz)</a></p>",
    "id": "0iurdfxAfRDdIC78oHCyPA",
    "images": [
        {
            "height": 640,
            "url": "https://i.scdn.co/image/ab6765630000ba8a9746faeb889192f74490be6c",
            "width": 640
        },
        {
            "height": 300,
            "url": "https://i.scdn.co/image/ab67656300005f1f9746faeb889192f74490be6c",
            "width": 300
        },
        {
            "height": 64,
            "url": "https://i.scdn.co/image/ab6765630000f68d9746faeb889192f74490be6c",
            "width": 64
        }
    ],
    "is_externally_hosted": false,
    "is_playable": true,
    "language": "en-US",
    "languages": [
        "en-US"
    ],
    "name": "Day 228: The Watchman's Duty (2022)",
    "release_date": "2022-08-16",
    "release_date_precision": "day",
    "resume_point": {
        "fully_played": false,
        "resume_position_ms": 0
    },
    "type": "episode",
    "uri": "spotify:episode:0iurdfxAfRDdIC78oHCyPA"
}