{
    "audio_preview_url": "https://podz-content.spotifycdn.com/audio/clips/1uNbD5Hg6qww9g2llx9Msv/clip_341212_401212.mp3",
    "description": "To support the\u00a0ministry and access exclusive content, go to: \u2060\u2060\u2060http://patreon.com/logicalbiblestudy\u2060\u2060\u2060 For complete verse-by-verse audio commentaries from Logical Bible Study, go to: \u2060\u2060\u2060https://mysoundwise.com/publishers/1677296682850p  John 15: 9-11 - 'Remain in my love.'  Catechism of the Catholic Church Paragraphs: - 1823 (in 'Charity') - Jesus makes charity the new commandment. By loving his own \"to the end,\" he makes manifest the Father's love which he receives. By loving one another, the disciples imitate the love of Jesus which they themselves receive. Whence Jesus says: \"As the Father has loved me, so have I loved you; abide in my love.\" and again: \"This is my commandment, that you love one another as I have loved you.\"  Got a Bible question? Send an email to logicalbiblestudy@gmail.com, and it will be answered in an upcoming episode!  ---   Send in a voice message: https://podcasters.spotify.com/pod/show/daily-gospel-exegesis/message",
    "duration_ms": 458594,
    "explicit": false,
    "external_urls": {
        "spotify": "https://open.spotify.com/episode/2EcGKmTO2rIgt1D4PJdZNZ"
    },
    "href": "https://api.spotify.com/v1/episodes/2EcGKmTO2rIgt1D4PJdZNZ",
    "html_description": "<p>To support the\u00a0ministry and access exclusive content, go to: <a href=\"https://www.patreon.com/logicalbiblestudy\" rel=\"nofollow\">\u2060\u2060\u2060http://patreon.com/logicalbiblestudy\u2060\u2060\u2060</a></p><br/><p>For complete verse-by-verse audio commentaries from Logical Bible Study, go to: <a href=\"https://mysoundwise.com/publishers/1677296682850p\" rel=\"nofollow\">\u2060\u2060\u2060https://mysoundwise.com/publishers/1677296682850p</a></p><br/><p><br /></p><br/><p>John 15: 9-11 - &#39;Remain in my love.&#39;</p><br/><p><br /></p><br/><p>Catechism of the Catholic Church Paragraphs:</p><br/><p>- 1823 (in &#39;Charity&#39;) - Jesus makes charity the new commandment. By loving his own &#34;to the end,&#34; he makes manifest the Father&#39;s love which he receives. By loving one another, the disciples imitate the love of Jesus which they themselves receive. Whence Jesus says: &#34;As the Father has loved me, so have I loved you; abide in my love.&#34; and again: &#34;This is my commandment, that you love one another as I have loved you.&#34;</p><br/><p><br /></p><br/><p>Got a Bible question? Send an email to logicalbiblestudy&#64;gmail.com, and it will be answered in an upcoming episode!</p><br/>--- <br/>Send in a voice message: https://podcasters.spotify.com/pod/show/daily-gospel-exegesis/message",
    "id": "2EcGKmTO2rIgt1D4PJdZNZ",
    "images": [
        {
            "height": 640,
            "url": "https://i.scdn.co/image/ab6765630000ba8aa10898a57fb4740a3aa6ef3f",
            "width": 640
        },
        {
            "height": 300,
            "url": "https://i.scdn.co/image/ab67656300005f1fa10898a57fb4740a3aa6ef3f",
            "width": 300
        },
        {
            "height": 64,
            "url": "https://i.scdn.co/image/ab6765630000f68da10898a57fb4740a3aa6ef3f",
            "width": 64
        }
    ],
    "is_externally_hosted": false,
    "is_playable": true,
    "language": "en",
    "languages": [
        "en"
    ],
    "name": "Thursday of Week 5 of Eastertide - John 15: 9-11",
    "release_date": "2023-05-10",
    "release_date_precision": "day",
    "resume_point": {
        "fully_played": false,
        "resume_position_ms": 0
    },
    "type": "episode",
    "uri": "spotify:episode:2EcGKmTO2rIgt1D4PJdZNZ"
}